flake8_array_spacing/__init__.py
flake8_array_spacing-0.2.0.dist-info/LICENSE
flake8_array_spacing-0.2.0.dist-info/METADATA
flake8_array_spacing-0.2.0.dist-info/WHEEL
flake8_array_spacing-0.2.0.dist-info/entry_points.txt
flake8_array_spacing-0.2.0.dist-info/top_level.txt
flake8_array_spacing-0.2.0.dist-info/RECORD
